LICENSE
README.md
setup.py
AnnotatedTree/ChunkType.py
AnnotatedTree/LayerInfo.c
AnnotatedTree/LayerInfo.pxd
AnnotatedTree/LayerInfo.pyx
AnnotatedTree/ParallelTreeBankDrawable.c
AnnotatedTree/ParallelTreeBankDrawable.pyx
AnnotatedTree/ParseNodeDrawable.c
AnnotatedTree/ParseNodeDrawable.pxd
AnnotatedTree/ParseNodeDrawable.pyx
AnnotatedTree/ParseTreeDrawable.c
AnnotatedTree/ParseTreeDrawable.pxd
AnnotatedTree/ParseTreeDrawable.pyx
AnnotatedTree/SearchType.py
AnnotatedTree/TreeBankDrawable.c
AnnotatedTree/TreeBankDrawable.pxd
AnnotatedTree/TreeBankDrawable.pyx
AnnotatedTree/__init__.py
AnnotatedTree/Layer/DependencyLayer.c
AnnotatedTree/Layer/DependencyLayer.pxd
AnnotatedTree/Layer/DependencyLayer.pyx
AnnotatedTree/Layer/EnglishPropbankLayer.c
AnnotatedTree/Layer/EnglishPropbankLayer.pxd
AnnotatedTree/Layer/EnglishPropbankLayer.pyx
AnnotatedTree/Layer/EnglishSemanticLayer.c
AnnotatedTree/Layer/EnglishSemanticLayer.pxd
AnnotatedTree/Layer/EnglishSemanticLayer.pyx
AnnotatedTree/Layer/EnglishWordLayer.c
AnnotatedTree/Layer/EnglishWordLayer.pxd
AnnotatedTree/Layer/EnglishWordLayer.pyx
AnnotatedTree/Layer/MetaMorphemeLayer.c
AnnotatedTree/Layer/MetaMorphemeLayer.pxd
AnnotatedTree/Layer/MetaMorphemeLayer.pyx
AnnotatedTree/Layer/MetaMorphemesMovedLayer.c
AnnotatedTree/Layer/MetaMorphemesMovedLayer.pxd
AnnotatedTree/Layer/MetaMorphemesMovedLayer.pyx
AnnotatedTree/Layer/MorphologicalAnalysisLayer.c
AnnotatedTree/Layer/MorphologicalAnalysisLayer.pxd
AnnotatedTree/Layer/MorphologicalAnalysisLayer.pyx
AnnotatedTree/Layer/MultiWordLayer.c
AnnotatedTree/Layer/MultiWordLayer.pxd
AnnotatedTree/Layer/MultiWordLayer.pyx
AnnotatedTree/Layer/MultiWordMultiItemLayer.c
AnnotatedTree/Layer/MultiWordMultiItemLayer.pxd
AnnotatedTree/Layer/MultiWordMultiItemLayer.pyx
AnnotatedTree/Layer/NERLayer.c
AnnotatedTree/Layer/NERLayer.pxd
AnnotatedTree/Layer/NERLayer.pyx
AnnotatedTree/Layer/PersianWordLayer.c
AnnotatedTree/Layer/PersianWordLayer.pxd
AnnotatedTree/Layer/PersianWordLayer.pyx
NlpToolkit_AnnotatedTree_Cy.egg-info/PKG-INFO
NlpToolkit_AnnotatedTree_Cy.egg-info/SOURCES.txt
NlpToolkit_AnnotatedTree_Cy.egg-info/dependency_links.txt
NlpToolkit_AnnotatedTree_Cy.egg-info/requires.txt
NlpToolkit_AnnotatedTree_Cy.egg-info/top_level.txt
nlptoolkit_annotatedtree_cy.egg-info/PKG-INFO
nlptoolkit_annotatedtree_cy.egg-info/SOURCES.txt
nlptoolkit_annotatedtree_cy.egg-info/dependency_links.txt
nlptoolkit_annotatedtree_cy.egg-info/requires.txt
nlptoolkit_annotatedtree_cy.egg-info/top_level.txt