Metadata-Version: 2.4
Name: nlptoolkit-annotatedtree-cy
Version: 1.0.16
Summary: Annotated constituency treebank library
Home-page: https://github.com/StarlangSoftware/AnnotatedTree-Cy
Author: olcaytaner
Author-email: olcay.yildiz@ozyegin.edu.tr
License-File: LICENSE
Requires-Dist: NlpToolkit-AnnotatedSentence-Cy
Requires-Dist: NlpToolkit-ParseTree-Cy
Dynamic: author
Dynamic: author-email
Dynamic: description
Dynamic: description-content-type
Dynamic: home-page
Dynamic: license-file
Dynamic: requires-dist
Dynamic: summary
